jformat/__init__.py
jformat/main.py
jformat/utils.py
demo_jformat-0.0.1.dist-info/LICENSE
demo_jformat-0.0.1.dist-info/METADATA
demo_jformat-0.0.1.dist-info/WHEEL
demo_jformat-0.0.1.dist-info/entry_points.txt
demo_jformat-0.0.1.dist-info/top_level.txt
demo_jformat-0.0.1.dist-info/RECORD
